edc_search/__init__.py
edc_search/apps.py
edc_search/constants.py
edc_search/model_mixins.py
edc_search/models.py
edc_search/search_slug.py
edc_search/updater.py
edc_search/urls.py
edc_search/wsgi.py
edc_search/tests/__init__.py
edc_search/tests/models.py
edc_search/tests/test_settings.py
edc_search/tests/etc/user-aes-local.key
edc_search/tests/etc/user-aes-restricted.key
edc_search/tests/etc/user-rsa-local-private.pem
edc_search/tests/etc/user-rsa-local-public.pem
edc_search/tests/etc/user-rsa-restricted-private.pem
edc_search/tests/etc/user-rsa-restricted-public.pem
edc_search/tests/etc/user-salt-local.key
edc_search/tests/etc/user-salt-restricted.key
edc_search/tests/tests/__init__.py
edc_search/tests/tests/tests.py
edc_search-1.0.1.dist-info/licenses/AUTHORS
edc_search-1.0.1.dist-info/licenses/LICENSE
edc_search-1.0.1.dist-info/METADATA
edc_search-1.0.1.dist-info/WHEEL
edc_search-1.0.1.dist-info/top_level.txt
edc_search-1.0.1.dist-info/RECORD
